wonder.py
wonder-0.1.0.dist-info/LICENSE
wonder-0.1.0.dist-info/METADATA
wonder-0.1.0.dist-info/WHEEL
wonder-0.1.0.dist-info/top_level.txt
wonder-0.1.0.dist-info/RECORD
