Metadata-Version: 2.1
Name: wonder
Version: 0.1.0
Summary: Python Game Engine
Home-page: https://github.com/hebi-python-ninja/wonder
Author: hebi-python-ninja
Author-email: hebi@python-ninja.com
License: MIT
Keywords: game,pygame,game engine,unity,box2d
Platform: UNKNOWN
Classifier: Development Status :: 3 - Alpha
Classifier: Intended Audience :: Developers
Classifier: Topic :: Games/Entertainment
Classifier: License :: OSI Approved :: MIT License
Classifier: Programming Language :: Python :: 3
Classifier: Programming Language :: Python :: 3.8
Classifier: Programming Language :: Python :: 3.9
License-File: LICENSE
Requires-Dist: pygame
Requires-Dist: Box2D
